Workbook

Sheet Assumptions
A1: Model Assumptions
A3: Item | B3: Value
A4: Opening Revenue | B4: 50000000
A5: Revenue growth | B5: 0.1
A6: COGS % of Revenue | B6: 0.6
A7: Operating expenses % | B7: 0.2
A8: Tax rate | B8: 0.25
A9: Receivable days | B9: 45
A10: Inventory days | B10: 60
A11: Payable days | B11: 30
A12: Annual Capex | B12: 2000000
A13: Interest rate | B13: 0.1
A14: Opening Debt | B14: 5000000
A15: Opening Cash | B15: 1000000

Sheet Income Statement
A3: Item | B3: Y1 | C3: Y2 | D3: Y3 | E3: Y4 | F3: Y5
A4: Revenue | B4: =Assumptions!B4 | C4: =B4*(1+Assumptions!B5) | D4: =C4*(1+Assumptions!B5) | E4: =D4*(1+Assumptions!B5) | F4: =E4*(1+Assumptions!B5)
A5: COGS | B5: =B4*Assumptions!B6 | C5: =C4*Assumptions!B6 | D5: =D4*Assumptions!B6 | E5: =E4*Assumptions!B6 | F5: =F4*Assumptions!B6
A6: Operating Expenses | B6: =B4*Assumptions!B7 | C6: =C4*Assumptions!B7 | D6: =D4*Assumptions!B7 | E6: =E4*Assumptions!B7 | F6: =F4*Assumptions!B7
A7: Depreciation | B7: =Assumptions!B12/5 | C7: =Assumptions!B12/5 | D7: =Assumptions!B12/5 | E7: =Assumptions!B12/5 | F7: =Assumptions!B12/5
A8: EBIT | B8: =B4-B5-B6-B7 | C8: =C4-C5-C6-C7 | D8: =D4-D5-D6-D7 | E8: =E4-E5-E6-E7 | F8: =F4-F5-F6-F7
A9: Interest | B9: =Assumptions!B13*Assumptions!B11 | C9: =Assumptions!B13*Assumptions!B11 | D9: =Assumptions!B13*Assumptions!B11 | E9: =Assumptions!B13*Assumptions!B11 | F9: =Assumptions!B13*Assumptions!B11
A10: EBT | B10: =B8-B9 | C10: =C8-C9 | D10: =D8-D9 | E10: =E8-E9 | F10: =F8-F9
A11: Tax | B11: =IF(B10>0,B10*Assumptions!B8,0) | C11: =IF(C10>0,C10*Assumptions!B8,0) | D11: =IF(D10>0,D10*Assumptions!B8,0) | E11: =IF(E10>0,E10*Assumptions!B8,0) | F11: =IF(F10>0,F10*Assumptions!B8,0)
A12: Net Income | B12: =B10-B11 | C12: =C10-C11 | D12: =D10-D11 | E12: =E10-E11 | F12: =F10-F11

Sheet Working Capital
A4: Accounts Receivable | B4: ='Income Statement'!B4*(Assumptions!B9/365) | C4: ='Income Statement'!C4*(Assumptions!B9/365) | D4: ='Income Statement'!D4*(Assumptions!B9/365) | E4: ='Income Statement'!E4*(Assumptions!B9/365) | F4: ='Income Statement'!F4*(Assumptions!B9/365)
A5: Inventory | B5: ='Income Statement'!B5*(Assumptions!B10/365) | C5: ='Income Statement'!C5*(Assumptions!B10/365) | D5: ='Income Statement'!D5*(Assumptions!B10/365) | E5: ='Income Statement'!E5*(Assumptions!B10/365) | F5: ='Income Statement'!F5*(Assumptions!B10/365)
A6: Accounts Payable | B6: ='Income Statement'!B5*(Assumptions!B11/365) | C6: ='Income Statement'!C5*(Assumptions!B11/365) | D6: ='Income Statement'!D5*(Assumptions!B11/365) | E6: ='Income Statement'!E5*(Assumptions!B11/365) | F6: ='Income Statement'!F5*(Assumptions!B11/365)
A7: Working Capital | B7: =B4+B5-B6 | C7: =C4+C5-C6 | D7: =D4+D5-D6 | E7: =E4+E5-E6 | F7: =F4+F5-F6
A8: Change in WC | B8: =B7 | C8: =C7-B7 | D8: =D7-C7 | E8: =E7-D7 | F8: =F7-E7

Sheet Cash Flow
A4: Net Income | B4: ='Income Statement'!B12 | C4: ='Income Statement'!C12 | D4: ='Income Statement'!D12 | E4: ='Income Statement'!E12 | F4: ='Income Statement'!F12
A5: Depreciation | B5: ='Income Statement'!B7 | C5: ='Income Statement'!C7 | D5: ='Income Statement'!D7 | E5: ='Income Statement'!E7 | F5: ='Income Statement'!F7
A6: Change in WC | B6: ='Working Capital'!B8 | C6: ='Working Capital'!C8 | D6: ='Working Capital'!D8 | E6: ='Working Capital'!E8 | F6: ='Working Capital'!F8
A7: Operating Cash Flow | B7: =B4+B5-B6 | C7: =C4+C5-C6 | D7: =D4+D5-D6 | E7: =E4+E5-E6 | F7: =F4+F5-F6
A8: Capex | B8: =Assumptions!B12 | C8: =Assumptions!B12 | D8: =Assumptions!B12 | E8: =Assumptions!B12 | F8: =Assumptions!B12
A9: Free Cash Flow | B9: =B7-B8 | C9: =C7-C8 | D9: =D7-D8 | E9: =E7-E8 | F9: =F7-F8
A10: Ending Cash | B10: =Assumptions!B14+B9 | C10: =B10+C9 | D10: =C10+D9 | E10: =D10+E9 | F10: =E10+F9

Sheet Balance Sheet
A4: Cash | B4: ='Cash Flow'!B10 | C4: ='Cash Flow'!C10 | D4: ='Cash Flow'!D10 | E4: ='Cash Flow'!E10 | F4: ='Cash Flow'!F10
A5: Accounts Receivable | B5: ='Working Capital'!B4 | C5: ='Working Capital'!C4 | D5: ='Working Capital'!D4 | E5: ='Working Capital'!E4 | F5: ='Working Capital'!F4
A6: Inventory | B6: ='Working Capital'!B5 | C6: ='Working Capital'!C5 | D6: ='Working Capital'!D5 | E6: ='Working Capital'!E5 | F6: ='Working Capital'!F5
A7: PP&E | B7: =Assumptions!B12 | C7: =B7+Assumptions!B12-'Income Statement'!C7 | D7: =C7+Assumptions!B12-'Income Statement'!D7 | E7: =D7+Assumptions!B12-'Income Statement'!E7 | F7: =E7+Assumptions!B12-'Income Statement'!F7
A8: Total Assets | B8: =SUM(B4:B7) | C8: =SUM(C4:C7) | D8: =SUM(D4:D7) | E8: =SUM(E4:E7) | F8: =SUM(F4:F7)
A9: Debt | B9: =Assumptions!B13 | C9: =Assumptions!B13 | D9: =Assumptions!B13 | E9: =Assumptions!B13 | F9: =Assumptions!B13
A10: Equity | B10: ='Income Statement'!B12 | C10: =B10+'Income Statement'!C12 | D10: =C10+'Income Statement'!D12 | E10: =D10+'Income Statement'!E12 | F10: =E10+'Income Statement'!F12
A11: Total Liab+Equity | B11: =B9+B10 | C11: =C9+C10 | D11: =D9+D10 | E11: =E9+E10 | F11: =F9+F10
