Workbook

Sheet Assumptions
A1: Project Assumptions
A3: Item | B3: Value
A4: Initial investment (plant & machinery) | B4: 25000000
A5: Project life (years) | B5: 5
A6: Units sold Year 1 (packs) | B6: 80000
A7: Annual sales growth | B7: 0.12
A8: Selling price per pack | B8: 220
A9: Variable cost per pack | B9: 130
A10: Fixed operating cost/year | B10: 4500000
A11: Tax rate | B11: 0.25
A12: Working capital (% of revenue) | B12: 0.1
A13: Discount rate (WACC) | B13: 0.12
A14: Salvage value (end of year 5) | B14: 4000000

Sheet Revenue Forecast
A1: Revenue Forecast
A3: Year | B3: Units Sold | C3: Price per Unit | D3: Revenue
A4: 1 | B4: =Assumptions!B6 | C4: =Assumptions!B8 | D4: =B4*C4
A5: 2 | B5: =B4*(1+Assumptions!B7) | C5: =Assumptions!B8 | D5: =B5*C5
A6: 3 | B6: =B5*(1+Assumptions!B7) | C6: =Assumptions!B8 | D6: =B6*C6
A7: 4 | B7: =B6*(1+Assumptions!B7) | C7: =Assumptions!B8 | D7: =B7*C7
A8: 5 | B8: =B7*(1+Assumptions!B7) | C8: =Assumptions!B8 | D8: =B8*C8

Sheet Cost Forecast
A1: Cost Forecast
A3: Year | B3: Revenue | C3: Variable Cost | D3: Fixed Cost | E3: Depreciation | F3: EBIT | G3: Tax | H3: EBIT After Tax
A4: 1 | B4: ='Revenue Forecast'!D4 | C4: ='Revenue Forecast'!B4*Assumptions!B9 | D4: =Assumptions!B10 | E4: =(Assumptions!B4-Assumptions!B13)/Assumptions!B5 | F4: =B4-C4-D4-E4 | G4: =IF(F4>0,F4*Assumptions!B11,0) | H4: =F4-G4
A5: 2 | B5: ='Revenue Forecast'!D5 | C5: ='Revenue Forecast'!B5*Assumptions!B9 | D5: =Assumptions!B10 | E5: =(Assumptions!B4-Assumptions!B13)/Assumptions!B5 | F5: =B5-C5-D5-E5 | G5: =IF(F5>0,F5*Assumptions!B11,0) | H5: =F5-G5
A6: 3 | B6: ='Revenue Forecast'!D6 | C6: ='Revenue Forecast'!B6*Assumptions!B9 | D6: =Assumptions!B10 | E6: =(Assumptions!B4-Assumptions!B13)/Assumptions!B5 | F6: =B6-C6-D6-E6 | G6: =IF(F6>0,F6*Assumptions!B11,0) | H6: =F6-G6
A7: 4 | B7: ='Revenue Forecast'!D7 | C7: ='Revenue Forecast'!B7*Assumptions!B9 | D7: =Assumptions!B10 | E7: =(Assumptions!B4-Assumptions!B13)/Assumptions!B5 | F7: =B7-C7-D7-E7 | G7: =IF(F7>0,F7*Assumptions!B11,0) | H7: =F7-G7
A8: 5 | B8: ='Revenue Forecast'!D8 | C8: ='Revenue Forecast'!B8*Assumptions!B9 | D8: =Assumptions!B10 | E8: =(Assumptions!B4-Assumptions!B13)/Assumptions!B5 | F8: =B8-C8-D8-E8 | G8: =IF(F8>0,F8*Assumptions!B11,0) | H8: =F8-G8

Sheet Free Cash Flow
A1: Free Cash Flow Calculation
A3: Year | B3: EBIT After Tax | C3: Depreciation | D3: Working Capital | E3: Change in WC | F3: Capex | G3: Salvage | H3: Free Cash Flow
A4: 0 | D4: ='Revenue Forecast'!D4*Assumptions!B12 | E4: =D4 | F4: =-Assumptions!B4 | G4: 0 | H4: =-D4+F4
A5: 1 | B5: ='Cost Forecast'!H4 | C5: ='Cost Forecast'!E4 | D5: ='Revenue Forecast'!D4*Assumptions!B12 | E5: =D5-D4 | F5: 0 | G5: 0 | H5: =B5+C5-E5+G5
A6: 2 | B6: ='Cost Forecast'!H5 | C6: ='Cost Forecast'!E5 | D6: ='Revenue Forecast'!D5*Assumptions!B12 | E6: =D6-D5 | F6: 0 | G6: 0 | H6: =B6+C6-E6+G6
A7: 3 | B7: ='Cost Forecast'!H6 | C7: ='Cost Forecast'!E6 | D7: ='Revenue Forecast'!D6*Assumptions!B12 | E7: =D7-D6 | F7: 0 | G7: 0 | H7: =B7+C7-E7+G7
A8: 4 | B8: ='Cost Forecast'!H7 | C8: ='Cost Forecast'!E7 | D8: ='Revenue Forecast'!D7*Assumptions!B12 | E8: =D8-D7 | F8: 0 | G8: 0 | H8: =B8+C8-E8+G8
A9: 5 | B9: ='Cost Forecast'!H8 | C9: ='Cost Forecast'!E8 | D9: ='Revenue Forecast'!D8*Assumptions!B12 | E9: =D9-D8 | F9: 0 | G9: =Assumptions!B13+D9 | H9: =B9+C9-E9+G9

Sheet NPV & IRR
A1: Investment Decision
A3: NPV | B3: =NPV(Assumptions!B12,'Free Cash Flow'!H5:H9)+'Free Cash Flow'!H4
A4: IRR | B4: =IRR('Free Cash Flow'!H4:H9)
A6: Decision Rule
A7: Accept if NPV > 0 and IRR > WACC
