Workbook

Sheet Income Statement
A1: Income Statement (Enter data in blue rows)
A3: Item | B3: Y-4 | C3: Y-3 | D3: Y-2 | E3: Y-1 | F3: Y
A4: Revenue
A5: COGS
A6: Gross Profit | B6: =B4-B5 | C6: =C4-C5 | D6: =D4-D5 | E6: =E4-E5 | F6: =F4-F5
A7: Operating Expenses
A8: EBITDA | B8: =B6-B7 | C8: =C6-C7 | D8: =D6-D7 | E8: =E6-E7 | F8: =F6-F7
A9: Depreciation
A10: EBIT | B10: =B8-B9 | C10: =C8-C9 | D10: =D8-D9 | E10: =E8-E9 | F10: =F8-F9
A11: Interest Expense
A12: EBT | B12: =B10-B11 | C12: =C10-C11 | D12: =D10-D11 | E12: =E10-E11 | F12: =F10-F11
A13: Tax
A14: Net Income | B14: =B12-B13 | C14: =C12-C13 | D14: =D12-D13 | E14: =E12-E13 | F14: =F12-F13

Sheet Balance Sheet
A1: Balance Sheet
A3: Item | B3: Y-4 | C3: Y-3 | D3: Y-2 | E3: Y-1 | F3: Y
A4: Cash
A5: Accounts Receivable
A6: Inventory
A7: Other Current Assets
A8: Total Current Assets | B8: =SUM(B4:B7) | C8: =SUM(C4:C7) | D8: =SUM(D4:D7) | E8: =SUM(E4:E7) | F8: =SUM(F4:F7)
A9: PP&E
A10: Other Noncurrent Assets
A11: Total Assets | B11: =B8+B9+B10 | C11: =C8+C9+C10 | D11: =D8+D9+D10 | E11: =E8+E9+E10 | F11: =F8+F9+F10
A12: Accounts Payable
A13: Short-term Debt
A14: Other Current Liabilities
A15: Total Current Liabilities | B15: =SUM(B12:B14) | C15: =SUM(C12:C14) | D15: =SUM(D12:D14) | E15: =SUM(E12:E14) | F15: =SUM(F12:F14)
A16: Long-term Debt
A17: Other Noncurrent Liabilities
A18: Total Liabilities | B18: =B15+B16+B17 | C18: =C15+C16+C17 | D18: =D15+D16+D17 | E18: =E15+E16+E17 | F18: =F15+F16+F17
A19: Equity
A20: Total Liabilities + Equity | B20: =B18+B19 | C20: =C18+C19 | D20: =D18+D19 | E20: =E18+E19 | F20: =F18+F19

Sheet Cash Flow Summary
A1: Cash Flow Summary
A3: Item | B3: Y-4 | C3: Y-3 | D3: Y-2 | E3: Y-1 | F3: Y
A4: Net Income | B4: ='Income Statement'!B14 | C4: ='Income Statement'!C14 | D4: ='Income Statement'!D14 | E4: ='Income Statement'!E14 | F4: ='Income Statement'!F14
A5: Depreciation
A6: Change in Working Capital
A7: Capex
A8: Free Cash Flow | B8: =B4+B5-B6-B7 | C8: =C4+C5-C6-C7 | D8: =D4+D5-D6-D7 | E8: =E4+E5-E6-E7 | F8: =F4+F5-F6-F7

Sheet Ratio Analysis
A1: Financial Ratios
A4: Gross Margin | B4: ='Income Statement'!B6/'Income Statement'!B4 | C4: ='Income Statement'!C6/'Income Statement'!C4 | D4: ='Income Statement'!D6/'Income Statement'!D4 | E4: ='Income Statement'!E6/'Income Statement'!E4 | F4: ='Income Statement'!F6/'Income Statement'!F4
A5: Operating Margin (EBIT) | B5: ='Income Statement'!B10/'Income Statement'!B4 | C5: ='Income Statement'!C10/'Income Statement'!C4 | D5: ='Income Statement'!D10/'Income Statement'!D4 | E5: ='Income Statement'!E10/'Income Statement'!E4 | F5: ='Income Statement'!F10/'Income Statement'!F4
A6: Net Profit Margin | B6: ='Income Statement'!B14/'Income Statement'!B4 | C6: ='Income Statement'!C14/'Income Statement'!C4 | D6: ='Income Statement'!D14/'Income Statement'!D4 | E6: ='Income Statement'!E14/'Income Statement'!E4 | F6: ='Income Statement'!F14/'Income Statement'!F4
A7: Current Ratio | B7: ='Balance Sheet'!B8/'Balance Sheet'!B15 | C7: ='Balance Sheet'!C8/'Balance Sheet'!C15 | D7: ='Balance Sheet'!D8/'Balance Sheet'!D15 | E7: ='Balance Sheet'!E8/'Balance Sheet'!E15 | F7: ='Balance Sheet'!F8/'Balance Sheet'!F15
A8: Quick Ratio | B8: =('Balance Sheet'!B4+'Balance Sheet'!B5)/'Balance Sheet'!B15 | C8: =('Balance Sheet'!C4+'Balance Sheet'!C5)/'Balance Sheet'!C15 | D8: =('Balance Sheet'!D4+'Balance Sheet'!D5)/'Balance Sheet'!D15 | E8: =('Balance Sheet'!E4+'Balance Sheet'!E5)/'Balance Sheet'!E15 | F8: =('Balance Sheet'!F4+'Balance Sheet'!F5)/'Balance Sheet'!F15
A9: Debt to Equity | B9: =('Balance Sheet'!B13+'Balance Sheet'!B12)/'Balance Sheet'!B19 | C9: =('Balance Sheet'!C13+'Balance Sheet'!C12)/'Balance Sheet'!C19 | D9: =('Balance Sheet'!D13+'Balance Sheet'!D12)/'Balance Sheet'!D19 | E9: =('Balance Sheet'!E13+'Balance Sheet'!E12)/'Balance Sheet'!E19 | F9: =('Balance Sheet'!F13+'Balance Sheet'!F12)/'Balance Sheet'!F19
A10: Interest Coverage | B10: ='Income Statement'!B10/'Income Statement'!B11 | C10: ='Income Statement'!C10/'Income Statement'!C11 | D10: ='Income Statement'!D10/'Income Statement'!D11 | E10: ='Income Statement'!E10/'Income Statement'!E11 | F10: ='Income Statement'!F10/'Income Statement'!F11
A11: Asset Turnover | B11: ='Income Statement'!B4/'Balance Sheet'!B11 | C11: ='Income Statement'!C4/'Balance Sheet'!C11 | D11: ='Income Statement'!D4/'Balance Sheet'!D11 | E11: ='Income Statement'!E4/'Balance Sheet'!E11 | F11: ='Income Statement'!F4/'Balance Sheet'!F11
A12: Inventory Turnover | B12: ='Income Statement'!B5/'Balance Sheet'!B6 | C12: ='Income Statement'!C5/'Balance Sheet'!C6 | D12: ='Income Statement'!D5/'Balance Sheet'!D6 | E12: ='Income Statement'!E5/'Balance Sheet'!E6 | F12: ='Income Statement'!F5/'Balance Sheet'!F6
A13: Receivable Days | B13: =('Balance Sheet'!B5/'Income Statement'!B4)*365 | C13: =('Balance Sheet'!C5/'Income Statement'!C4)*365 | D13: =('Balance Sheet'!D5/'Income Statement'!D4)*365 | E13: =('Balance Sheet'!E5/'Income Statement'!E4)*365 | F13: =('Balance Sheet'!F5/'Income Statement'!F4)*365
A14: Working Capital Cycle | B14: =('Balance Sheet'!B6/'Income Statement'!B5)*365+('Balance Sheet'!B5/'Income Statement'!B4)*365-('Balance Sheet'!B12/'Income Statement'!B5)*365 | C14: =('Balance Sheet'!C6/'Income Statement'!C5)*365+('Balance Sheet'!C5/'Income Statement'!C4)*365-('Balance Sheet'!C12/'Income Statement'!C5)*365 | D14: =('Balance Sheet'!D6/'Income Statement'!D5)*365+('Balance Sheet'!D5/'Income Statement'!D4)*365-('Balance Sheet'!D12/'Income Statement'!D5)*365 | E14: =('Balance Sheet'!E6/'Income Statement'!E5)*365+('Balance Sheet'!E5/'Income Statement'!E4)*365-('Balance Sheet'!E12/'Income Statement'!E5)*365 | F14: =('Balance Sheet'!F6/'Income Statement'!F5)*365+('Balance Sheet'!F5/'Income Statement'!F4)*365-('Balance Sheet'!F12/'Income Statement'!F5)*365

Sheet DuPont Analysis
A1: DuPont ROE Decomposition
A4: Net Profit Margin | B4: ='Income Statement'!B14/'Income Statement'!B4 | C4: ='Income Statement'!C14/'Income Statement'!C4 | D4: ='Income Statement'!D14/'Income Statement'!D4 | E4: ='Income Statement'!E14/'Income Statement'!E4 | F4: ='Income Statement'!F14/'Income Statement'!F4
A5: Asset Turnover | B5: ='Income Statement'!B4/'Balance Sheet'!B11 | C5: ='Income Statement'!C4/'Balance Sheet'!C11 | D5: ='Income Statement'!D4/'Balance Sheet'!D11 | E5: ='Income Statement'!E4/'Balance Sheet'!E11 | F5: ='Income Statement'!F4/'Balance Sheet'!F11
A6: Equity Multiplier | B6: ='Balance Sheet'!B11/'Balance Sheet'!B19 | C6: ='Balance Sheet'!C11/'Balance Sheet'!C19 | D6: ='Balance Sheet'!D11/'Balance Sheet'!D19 | E6: ='Balance Sheet'!E11/'Balance Sheet'!E19 | F6: ='Balance Sheet'!F11/'Balance Sheet'!F19
A7: ROE | B7: =B4*B5*B6 | C7: =C4*C5*C6 | D7: =D4*D5*D6 | E7: =E4*E5*E6 | F7: =F4*F5*F6
