Workbook

Sheet Assumptions
A1: Valuation Assumptions
A3: Item | B3: Value
A4: Revenue Growth | B4: 0.08
A5: EBIT Margin | B5: 0.22
A6: Tax Rate | B6: 0.25
A7: Depreciation (% of Revenue) | B7: 0.04
A8: Capex (% of Revenue) | B8: 0.05
A9: Working Capital (% of Revenue) | B9: 0.08
A10: WACC | B10: 0.11
A11: Terminal Growth | B11: 0.04
A12: Debt | B12: 5000000000
A13: Cash | B13: 1500000000
A14: Shares Outstanding | B14: 964157160

Sheet Revenue Forecast
A1: Revenue Projection
A3: Year | B3: Revenue
A4: Y1 | B4: 20000000000
A5: Y2 | B5: =B4*(1+Assumptions!B4)
A6: Y3 | B6: =B5*(1+Assumptions!B4)
A7: Y4 | B7: =B6*(1+Assumptions!B4)
A8: Y5 | B8: =B7*(1+Assumptions!B4)

Sheet Operating Forecast
A4: Revenue | B4: ='Revenue Forecast'!B4 | C4: B4*Assumptions!B5 | D4: C4*(1-Assumptions!B6) | E4: B4*Assumptions!B7
A5: EBIT | B5: ='Revenue Forecast'!B5 | C5: B5*Assumptions!B5 | D5: C5*(1-Assumptions!B6) | E5: B5*Assumptions!B7
A6: NOPAT | B6: ='Revenue Forecast'!B6 | C6: B6*Assumptions!B5 | D6: C6*(1-Assumptions!B6) | E6: B6*Assumptions!B7
A7: Depreciation | B7: ='Revenue Forecast'!B7 | C7: B7*Assumptions!B5 | D7: C7*(1-Assumptions!B6) | E7: B7*Assumptions!B7
B8: ='Revenue Forecast'!B8 | C8: B8*Assumptions!B5 | D8: C8*(1-Assumptions!B6) | E8: B8*Assumptions!B7

Sheet Free Cash Flow
A4: NOPAT | B4: ='Operating Forecast'!D4 | C4: ='Operating Forecast'!E4 | D4: ='Operating Forecast'!B4*Assumptions!B8 | E4: ='Operating Forecast'!B4*Assumptions!B9 | F4: B4+C4-D4-E4
A5: Depreciation | B5: ='Operating Forecast'!D5 | C5: ='Operating Forecast'!E5 | D5: ='Operating Forecast'!B5*Assumptions!B8 | E5: =('Operating Forecast'!B5-'Operating Forecast'!B4)*Assumptions!B9 | F5: B5+C5-D5-E5
A6: Capex | B6: ='Operating Forecast'!D6 | C6: ='Operating Forecast'!E6 | D6: ='Operating Forecast'!B6*Assumptions!B8 | E6: =('Operating Forecast'!B6-'Operating Forecast'!B5)*Assumptions!B9 | F6: B6+C6-D6-E6
A7: Change in WC | B7: ='Operating Forecast'!D7 | C7: ='Operating Forecast'!E7 | D7: ='Operating Forecast'!B7*Assumptions!B8 | E7: =('Operating Forecast'!B7-'Operating Forecast'!B6)*Assumptions!B9 | F7: B7+C7-D7-E7
A8: FCF | B8: ='Operating Forecast'!D8 | C8: ='Operating Forecast'!E8 | D8: ='Operating Forecast'!B8*Assumptions!B8 | E8: =('Operating Forecast'!B8-'Operating Forecast'!B7)*Assumptions!B9 | F8: B8+C8-D8-E8

Sheet DCF Valuation
A1: DCF Valuation
A4: Present Value of FCF | B4: ='Free Cash Flow'!F4/(1+Assumptions!B10)^1
B5: ='Free Cash Flow'!F5/(1+Assumptions!B10)^2
B6: ='Free Cash Flow'!F6/(1+Assumptions!B10)^3
B7: ='Free Cash Flow'!F7/(1+Assumptions!B10)^4
B8: ='Free Cash Flow'!F8/(1+Assumptions!B10)^5
A10: Terminal Value | B10: =('Free Cash Flow'!F8*(1+Assumptions!B11))/(Assumptions!B10-Assumptions!B11)
A11: PV Terminal Value | B11: =B10/(1+Assumptions!B10)^5
A13: Enterprise Value | B13: =SUM(B4:B8)+B11
A14: Equity Value | B14: =B13-Assumptions!B12+Assumptions!B13
A15: Intrinsic Value Per Share | B15: =B14/Assumptions!B14

Sheet Sensitivity
A1: Sensitivity Analysis (WACC vs Growth)
