Workbook

Sheet Survey Data
A1: Willingness-to-Pay Survey
A3: Price (₹) | B3: % Willing to Buy
A4: 180 | B4: 0.82
A5: 200 | B5: 0.7
A6: 220 | B6: 0.58
A7: 240 | B7: 0.44
A8: 260 | B8: 0.31
A9: 280 | B9: 0.2

Sheet Demand Curve
A1: Demand Estimation
A3: Price (₹) | B3: Purchase % | C3: Estimated Units Sold | D3: Market Size | E3: 50000
A4: ='Survey Data'!A4 | B4: ='Survey Data'!B4 | C4: =B4*$E$3
A5: ='Survey Data'!A5 | B5: ='Survey Data'!B5 | C5: =B5*$E$3
A6: ='Survey Data'!A6 | B6: ='Survey Data'!B6 | C6: =B6*$E$3
A7: ='Survey Data'!A7 | B7: ='Survey Data'!B7 | C7: =B7*$E$3
A8: ='Survey Data'!A8 | B8: ='Survey Data'!B8 | C8: =B8*$E$3
A9: ='Survey Data'!A9 | B9: ='Survey Data'!B9 | C9: =B9*$E$3

Sheet Revenue Simulation
A1: Revenue Calculation
A3: Price | B3: Units Sold | C3: Revenue | E3: Max Revenue
A4: ='Demand Curve'!A4 | B4: ='Demand Curve'!C4 | C4: =A4*B4 | E4: =MAX(C4:C9)
A5: ='Demand Curve'!A5 | B5: ='Demand Curve'!C5 | C5: =A5*B5
A6: ='Demand Curve'!A6 | B6: ='Demand Curve'!C6 | C6: =A6*B6
A7: ='Demand Curve'!A7 | B7: ='Demand Curve'!C7 | C7: =A7*B7
A8: ='Demand Curve'!A8 | B8: ='Demand Curve'!C8 | C8: =A8*B8
A9: ='Demand Curve'!A9 | B9: ='Demand Curve'!C9 | C9: =A9*B9

Sheet Profit Sensitivity
A1: Profit Analysis
A3: Price | B3: Units Sold | C3: Contribution Margin | D3: Total Profit | E3: Cost per Unit | F3: 130 | H3: Max Profit
A4: ='Demand Curve'!A4 | B4: ='Demand Curve'!C4 | C4: =A4-$F$3 | D4: =C4*B4 | H4: =MAX(D4:D9)
A5: ='Demand Curve'!A5 | B5: ='Demand Curve'!C5 | C5: =A5-$F$3 | D5: =C5*B5
A6: ='Demand Curve'!A6 | B6: ='Demand Curve'!C6 | C6: =A6-$F$3 | D6: =C6*B6
A7: ='Demand Curve'!A7 | B7: ='Demand Curve'!C7 | C7: =A7-$F$3 | D7: =C7*B7
A8: ='Demand Curve'!A8 | B8: ='Demand Curve'!C8 | C8: =A8-$F$3 | D8: =C8*B8
A9: ='Demand Curve'!A9 | B9: ='Demand Curve'!C9 | C9: =A9-$F$3 | D9: =C9*B9
